setup.py
deel/__init__.py
deel/agentServer.py
deel/commands.py
deel/deel.py
deel/tensor.py
deel.egg-info/PKG-INFO
deel.egg-info/SOURCES.txt
deel.egg-info/dependency_links.txt
deel.egg-info/pbr.json
deel.egg-info/requires.txt
deel.egg-info/top_level.txt
deel/model/VGG16.py
deel/model/__init__.py
deel/model/anchor_target.py
deel/model/bbox_transform.py
deel/model/caffefunction.py
deel/model/faster_rcnn.py
deel/model/generate_anchors.py
deel/model/googlenet.py
deel/model/lstm.py
deel/model/nin.py
deel/model/proposal_layer.py
deel/model/q_net.py
deel/model/rnin.py
deel/model/roi_pooling_2d.py
deel/network/__init__.py
deel/network/alexnet.py
deel/network/caffenet.py
deel/network/dqn.py
deel/network/fasterRCNN.py
deel/network/googlenet.py
deel/network/nin.py
deel/network/resnet152.py
deel/network/rnin.py