Metadata-Version: 1.0
Name: deel
Version: 0.0.4.4
Summary: Deel; A High level deep learning description language
Home-page: https://github.com/uei/deel
Author: UEI corporation
Author-email: info@uei.co.jp
License: MIT
Keywords: chainer
Platform: UNKNOWN
